setup.py
eko_probability01/Binomialdistribution.py
eko_probability01/Gaussiandistribution.py
eko_probability01/Generaldistribution.py
eko_probability01/__init__.py
eko_probability01.egg-info/PKG-INFO
eko_probability01.egg-info/SOURCES.txt
eko_probability01.egg-info/dependency_links.txt
eko_probability01.egg-info/not-zip-safe
eko_probability01.egg-info/top_level.txt